README.rst
setup.py
pypratico_exercicio_xml/__init__.py
pypratico_exercicio_xml/resolucao.py
pypratico_exercicio_xml.egg-info/PKG-INFO
pypratico_exercicio_xml.egg-info/SOURCES.txt
pypratico_exercicio_xml.egg-info/dependency_links.txt
pypratico_exercicio_xml.egg-info/not-zip-safe
pypratico_exercicio_xml.egg-info/requires.txt
pypratico_exercicio_xml.egg-info/top_level.txt
pypratico_exercicio_xml/__pycache__/__init__.cpython-36.pyc