Metadata-Version: 1.1
Name: pypratico-exercicio-xml
Version: 0.4
Summary: Pacote criado para exercicio do curso PyPratico
Home-page: https://github.com/mroratobaptista/exercicio-pypratico-pyup-travis-flake8
Author: Matheus Rorato Baptista
Author-email: matheusrorato@gmail.com
License: AGPL
Platform: UNKNOWN
Classifier: Development Status :: 4 - Beta
Classifier: Environment :: Web Environment
Classifier: Intended Audience :: Developers
Classifier: License :: OSI Approved :: GNU Affero General Public License v3 or later (AGPLv3+)
Classifier: Operating System :: OS Independent
Classifier: Programming Language :: Python
Classifier: Framework :: Paste
